prog_shojin_util/__init__.py
prog_shojin_util/__main__.py
prog_shojin_util/cli.py
prog_shojin_util/cli_config.py
prog_shojin_util/logging_config.py
prog_shojin_util/scraper/__init__.py
prog_shojin_util/scraper/link_collector.py
prog_shojin_util/services/output_formatter.py
prog_shojin_util/services/problem_finder.py
prog_shojin_util/utils/__init__.py
prog_shojin_util/utils/cache.py
prog_shojin_util/utils/contest_site_factory.py
prog_shojin_util/utils/contest_sites/__init__.py
prog_shojin_util/utils/contest_sites/abstract/__init__.py
prog_shojin_util/utils/contest_sites/abstract/api.py
prog_shojin_util/utils/contest_sites/abstract/matcher.py
prog_shojin_util/utils/contest_sites/abstract/parser.py
prog_shojin_util/utils/contest_sites/api_utils.py
prog_shojin_util/utils/contest_sites/atcoder/__init__.py
prog_shojin_util/utils/contest_sites/atcoder/api.py
prog_shojin_util/utils/contest_sites/atcoder/matcher.py
prog_shojin_util/utils/contest_sites/atcoder/parser.py
prog_shojin_util/utils/contest_sites/classifier.py
prog_shojin_util/utils/contest_sites/topcoder/__init__.py
prog_shojin_util/utils/contest_sites/topcoder/matcher.py
prog_shojin_util/utils/contest_sites/yukicoder/__init__.py
prog_shojin_util/utils/contest_sites/yukicoder/api.py
prog_shojin_util/utils/contest_sites/yukicoder/matcher.py
prog_shojin_util/utils/contest_sites/yukicoder/parser.py
prog_shojin_util/utils/url_tools.py
prog_shojin_util-0.1.1.dist-info/LICENSE
prog_shojin_util-0.1.1.dist-info/METADATA
prog_shojin_util-0.1.1.dist-info/WHEEL
prog_shojin_util-0.1.1.dist-info/entry_points.txt
prog_shojin_util-0.1.1.dist-info/RECORD
