Metadata-Version: 2.1
Name: prog-shojin-util
Version: 0.1.1
Summary: extracting and filtering problems from AtCoder, Yukicoder, and more.
Home-page: https://github.com/edge2992/prog_shojin_util
License: MIT
Author: Kazuya Isawa
Author-email: torune.summer@gmail.com
Requires-Python: >=3.9,<4.0
Classifier: License :: OSI Approved :: MIT License
Classifier: Programming Language :: Python :: 3
Classifier: Programming Language :: Python :: 3.9
Classifier: Programming Language :: Python :: 3.10
Classifier: Programming Language :: Python :: 3.11
Provides-Extra: docs
Requires-Dist: Sphinx[docs] (>=4.3.2,<5.0.0) ; extra == "docs"
Requires-Dist: beautifulsoup4 (>=4.12.2,<5.0.0)
Requires-Dist: click (>=8.1.6,<9.0.0)
Requires-Dist: pandas (>=2.0.3,<3.0.0)
Requires-Dist: requests (>=2.31.0,<3.0.0)
Requires-Dist: sphinx-autodoc-typehints[docs] (==1.12.0) ; extra == "docs"
Requires-Dist: sphinx-rtd-theme[docs] (>=1.0.0,<2.0.0) ; extra == "docs"
Requires-Dist: tabulate (>=0.9.0,<0.10.0)
Project-URL: Repository, https://github.com/edge2992/prog_shojin_util
